setup.py
njtest/hello.py
njtest.egg-info/PKG-INFO
njtest.egg-info/SOURCES.txt
njtest.egg-info/dependency_links.txt
njtest.egg-info/entry_points.txt
njtest.egg-info/requires.txt
njtest.egg-info/top_level.txt
njtest.egg-info/zip-safe
njtest/common/nj_cmd.py
njtest/common/nj_email.py
njtest/common/nj_excel.py
njtest/common/nj_file.py
njtest/common/nj_logcat.py
njtest/reptle/demo.py
njtest/reptle/nj_ip.py
njtest/serial/nj_serial.py
njtest/serial/nj_serial_email.py
njtest/serial/serial_count.py
njtest/serial/serial_crc.py
njtest/sql/demo.py
njtest/sql/new_onsql.py
njtest/test/ALi.py
njtest/test/BL.py
njtest/test/HuaWei.py
njtest/test/JD.py
njtest/test/System.py
njtest/ui2/browser.py
njtest/ui2/mobile.py
njtest/use/jd_power.py
njtest/use/serial_115200.py
njtest/use/serial_9600.py
njtest/utils/nj_parse.py
njtest/utils/nj_re.py
njtest/utils/nj_time.py