Metadata-Version: 1.0
Name: njtest
Version: 1.462
Summary: Automated Packaging Tool
Home-page: https://github.com/congrenya/njtest/blob/master/njtest.py
Author: Stephen Yao
Author-email: a1123547734@163.com
License: MIT Licence
Keywords: pip,SICA,featureextraction
Platform: any
